{
  "[URL_BASE_TOPICS]": "/support/kb/",
  "[FRONTMATTER_TRANSLATIONKEY]": "https://www.uptrends.com/support/kb/monitor-settings/bandwidth-throttling",
  "[IMAGE_URL_1]": "/img/content/scr-fpc-bandwidth-browser.min.png",
  "[IMAGE_URL_2]": "/img/content/scr-fpc-bandwidth-simulated.min.png",
  "[LINK_URL_1]": "[IMAGE_URL_1]",
  "[LINK_URL_2]": "[IMAGE_URL_2]",
  "[SHORTCODE_1]": "{{< AppElement type=\"tab\" >}}",
  "[SHORTCODE_2]": "{{< /AppElement >}}",
  "[SHORTCODE_3]": "{{< AppElement type=\"menuitem\" >}}",
  "[SHORTCODE_4]": "{{< /AppElement >}}",
  "[SHORTCODE_5]": "{{< AppElement type=\"menuitem\" >}}",
  "[SHORTCODE_6]": "{{< /AppElement >}}",
  "[SHORTCODE_7]": "{{< AppElement type=\"savebutton\" >}}",
  "[SHORTCODE_8]": "{{< /AppElement >}}",
  "[SHORTCODE_9]": "{{< AppElement type=\"tab\" >}}",
  "[SHORTCODE_10]": "{{< /AppElement >}}",
  "[SHORTCODE_11]": "{{< AppElement type=\"menuitem\" >}}",
  "[SHORTCODE_12]": "{{< /AppElement >}}",
  "[SHORTCODE_13]": "{{< AppElement type=\"menuitem\" >}}",
  "[SHORTCODE_14]": "{{< /AppElement >}}",
  "[SHORTCODE_15]": "{{< AppElement type=\"savebutton\" >}}",
  "[SHORTCODE_16]": "{{< /AppElement >}}"
}