{
  "[URL_BASE_TOPICS]": "/support/kb/",
  "[FRONTMATTER_TRANSLATIONKEY]": "https://www.uptrends.com/support/kb/monitor-settings/dynamic-values-in-url-and-post-content",
  "[LINK_URL_1]": "{{< ref path=\"support/kb/synthetic-monitoring/transactions/automatic-variables#date-and-time\" lang=\"en\" >}}",
  "[LINK_URL_2]": "{{< ref path=\"support/kb/synthetic-monitoring/transactions/automatic-variables\" lang=\"en\" >}}",
  "[LINK_URL_3]": "{{< ref path=\"support/kb/synthetic-monitoring/transactions/automatic-variables#random-unique-identifier\" lang=\"en\" >}}",
  "[SHORTCODE_1]": "{{< callout >}}",
  "[SHORTCODE_2]": "{{< /callout >}}",
  "[SYSTEM_VAR_1]": "{{@DateTime(dd-MM-yyyy)}}",
  "[SYSTEM_VAR_2]": "{{@RandomGuid}}",
  "[SYSTEM_VAR_3]": "{{@RandomGuid}}",
  "[INLINE_CODE_1]": "`... <StartDate>2023-02-27</StartDate> ...`",
  "[INLINE_CODE_2]": "`... <StartDate>[SYSTEM_VAR_1]</StartDate> ...`",
  "[INLINE_CODE_3]": "`[SYSTEM_VAR_2]`",
  "[INLINE_CODE_4]": "`http://www.example.com?myvalue=[SYSTEM_VAR_3]`",
  "[INLINE_CODE_5]": "`http://www.example.com?myvalue=37f1f109-58a2-4bea-adfb-9aed54619453`"
}