{
  "[URL_BASE_TOPICS]": "/support/kb/",
  "[FRONTMATTER_TRANSLATIONKEY]": "https://www.uptrends.com/support/kb/api-monitoring/multi-step",
  "[IMAGE_URL_1]": "/img/content/scr-msa-example-steps.min.png",
  "[IMAGE_URL_2]": "/img/content/scr-msa-editor-request-tab.min.png",
  "[IMAGE_URL_3]": "/img/content/scr-MSA-headers-default_override_auth.min.png",
  "[IMAGE_URL_4]": "/img/content/scr-MSA-vault-creds-references.min.png",
  "[IMAGE_URL_5]": "/img/content/scr-tls-versions-option-checkbox.min.png",
  "[IMAGE_URL_6]": "/img/content/scr-msa-step-http-version.min.png",
  "[IMAGE_URL_7]": "/img/content/scr-msa-curl-import-result.min.png",
  "[IMAGE_URL_8]": "/img/content/scr-MSA-editor-response-tab.min.png",
  "[IMAGE_URL_9]": "/img/content/scr_MSA_file-upload-picker.png",
  "[IMAGE_URL_10]": "/img/content/scr_MSA_file-upload-headers-example.png",
  "[LINK_URL_1]": "{{< ref path=\"/support/kb/synthetic-monitoring/api-monitoring/multi-step-variables#predefined\" lang=\"nl\" >}}",
  "[LINK_URL_2]": "{{< ref path=\"/support/kb/synthetic-monitoring/api-monitoring/user-defined-functions\" lang=\"nl\" >}}",
  "[LINK_URL_3]": "{{< ref path=\"/support/kb/synthetic-monitoring/api-monitoring/multi-step-custom-scripting\" lang=\"nl\" >}}",
  "[LINK_URL_4]": "{{< ref path=\"support/kb/synthetic-monitoring/api-monitoring/multi-step-authentication\" lang=\"nl\" >}}",
  "[LINK_URL_5]": "{{< ref path=\"support/kb/synthetic-monitoring/api-monitoring/multi-step-monitoring-client-certificate-authentication\" lang=\"nl\" >}}",
  "[LINK_URL_6]": "{{< ref path=\"support/kb/synthetic-monitoring/api-monitoring/multi-step-assertions\" lang=\"nl\" >}}",
  "[LINK_URL_7]": "{{< ref path=\"support/kb/synthetic-monitoring/api-monitoring/multi-step-variables\" lang=\"nl\" >}}",
  "[LINK_URL_8]": "{{< ref path=\"/support/kb/synthetic-monitoring/api-monitoring/multi-step-variables#predefined\" lang=\"nl\" >}}",
  "[LINK_URL_9]": "{{< ref path=\"/support/kb/synthetic-monitoring/api-monitoring/user-defined-functions\" lang=\"nl\" >}}",
  "[LINK_URL_10]": "{{< ref path=\"/support/kb/synthetic-monitoring/api-monitoring/custom-api-metrics-setup\" lang=\"nl\" >}}",
  "[LINK_URL_11]": "{{< ref path=\"/support/kb/synthetic-monitoring/api-monitoring/hashing-and-encoding\" lang=\"nl\" >}}",
  "[LINK_URL_12]": "{{< ref path=\"support/kb/synthetic-monitoring/monitor-settings/check-interval-explained\" lang=\"nl\" >}}",
  "[LINK_URL_13]": "[IMAGE_URL_1]",
  "[LINK_URL_14]": "[IMAGE_URL_2]",
  "[LINK_URL_15]": "{{< ref path=\"contact\" lang=\"nl\" >}}",
  "[LINK_URL_16]": "{{< ref path=\"/support/kb/api/vault-api\" lang=\"nl\" >}}",
  "[LINK_URL_17]": "{{< ref path=\"/support/kb/api/vault-api\" lang=\"nl\" >}}",
  "[LINK_URL_18]": "{{< ref path=\"/support/kb/api/vault-api\" lang=\"nl\" >}}",
  "[LINK_URL_19]": "[IMAGE_URL_3]",
  "[LINK_URL_20]": "{{< ref path=\"support/kb/synthetic-monitoring/api-monitoring/multi-step-variables\" lang=\"nl\" >}}",
  "[LINK_URL_21]": "{{< ref path=\"support/kb/synthetic-monitoring/api-monitoring/multi-step-authentication\" lang=\"nl\" >}}",
  "[LINK_URL_22]": "{{< ref path=\"support/kb/account/vault#credential-set\" lang=\"nl\" >}}",
  "[LINK_URL_23]": "[IMAGE_URL_4]",
  "[LINK_URL_24]": "{{< ref path=\"/support/kb/synthetic-monitoring/checkpoints\" lang=\"nl\" >}}",
  "[LINK_URL_25]": "[IMAGE_URL_5]",
  "[LINK_URL_26]": "[IMAGE_URL_6]",
  "[LINK_URL_27]": "https://www.galacticresorts.com",
  "[LINK_URL_28]": "[IMAGE_URL_7]",
  "[LINK_URL_29]": "[IMAGE_URL_8]",
  "[LINK_URL_30]": "{{< ref path=\"support/kb/synthetic-monitoring/api-monitoring/multi-step-assertions\" lang=\"nl\" >}}",
  "[LINK_URL_31]": "{{< ref path=\"support/kb/synthetic-monitoring/api-monitoring/multi-step-variables\" lang=\"nl\" >}}",
  "[LINK_URL_32]": "{{< ref path=\"support/kb/account/vault\" lang=\"nl\" >}}",
  "[LINK_URL_33]": "{{< ref path=\"support/kb/account/vault#file\" lang=\"nl\" >}}",
  "[LINK_URL_34]": "[IMAGE_URL_9]",
  "[LINK_URL_35]": "[IMAGE_URL_10]",
  "[SHORTCODE_1]": "{{< callout >}}",
  "[SHORTCODE_2]": "{{< /callout >}}",
  "[SHORTCODE_3]": "{{< callout >}}",
  "[SHORTCODE_4]": "{{< /callout >}}",
  "[SHORTCODE_5]": "{{< callout >}}",
  "[SHORTCODE_6]": "{{< /callout >}}",
  "[SHORTCODE_7]": "{{< AppElement type=\"menuitem\" >}}",
  "[SHORTCODE_8]": "{{< /AppElement >}}",
  "[SHORTCODE_9]": "{{< AppElement type=\"iconAdd\" >}}",
  "[SHORTCODE_10]": "{{< /AppElement >}}",
  "[SHORTCODE_11]": "{{< AppElement type=\"button\" >}}",
  "[SHORTCODE_12]": "{{< /AppElement >}}",
  "[SHORTCODE_13]": "{{< AppElement type=\"tab\" >}}",
  "[SHORTCODE_14]": "{{< /AppElement >}}",
  "[SHORTCODE_15]": "{{< AppElement type=\"buttonPrimary\" >}}",
  "[SHORTCODE_16]": "{{< /AppElement >}}",
  "[SHORTCODE_17]": "{{< AppElement type=\"tab\" >}}",
  "[SHORTCODE_18]": "{{< /AppElement >}}",
  "[SHORTCODE_19]": "{{< AppElement type=\"buttonSecondary\" >}}",
  "[SHORTCODE_20]": "{{< /AppElement >}}",
  "[SHORTCODE_21]": "{{< AppElement type=\"tab\" >}}",
  "[SHORTCODE_22]": "{{< /AppElement >}}",
  "[SHORTCODE_23]": "{{< AppElement type=\"buttonSecondary\" >}}",
  "[SHORTCODE_24]": "{{< /AppElement >}}",
  "[SHORTCODE_25]": "{{< AppElement type=\"buttonPrimary\" >}}",
  "[SHORTCODE_26]": "{{< /AppElement >}}",
  "[SHORTCODE_27]": "{{< AppElement type=\"buttonPrimary\" >}}",
  "[SHORTCODE_28]": "{{< /AppElement >}}",
  "[SHORTCODE_29]": "{{< AppElement type=\"button\" >}}",
  "[SHORTCODE_30]": "{{< /AppElement >}}",
  "[SHORTCODE_31]": "{{< AppElement type=\"buttonSecondary\" >}}",
  "[SHORTCODE_32]": "{{< /AppElement >}}",
  "[SHORTCODE_33]": "{{< AppElement type=\"button\" >}}",
  "[SHORTCODE_34]": "{{< /AppElement >}}",
  "[SHORTCODE_35]": "{{< AppElement type=\"buttonSecondary\" >}}",
  "[SHORTCODE_36]": "{{< /AppElement >}}",
  "[SHORTCODE_37]": "{{< Code/Symbol type=\"variable\" >}}",
  "[SHORTCODE_38]": "{{< /Code/Symbol >}}",
  "[SHORTCODE_39]": "{{< Code/Symbol type=\"source\" >}}",
  "[SHORTCODE_40]": "{{< /Code/Symbol >}}",
  "[SHORTCODE_41]": "{{< Code/Symbol type=\"property\" >}}",
  "[SHORTCODE_42]": "{{< /Code/Symbol >}}",
  "[SHORTCODE_43]": "{{< Code/Symbol type=\"comparison\" >}}",
  "[SHORTCODE_44]": "{{< /Code/Symbol >}}",
  "[SHORTCODE_45]": "{{< Code/Symbol type=\"target\" >}}",
  "[SHORTCODE_46]": "{{< /Code/Symbol >}}",
  "[SYSTEM_VAR_1]": "{{@VaultItem.<itemGuid>.Password}}",
  "[SYSTEM_VAR_2]": "{{@VaultItem.<itemGuid>.Username}}",
  "[CODE_BLOCK_1]": "```\ncurl -X POST https://www.galacticresorts.com/api/Reservation -H \"Content-Type: application/x-www-form-urlencoded\" -u username:password -d \"name=Joe&productId=97f8fcc9-11b5-4d86-b208-ccb6d2be35e3&sols=5\"\n```",
  "[INLINE_CODE_1]": "`Content-Type`",
  "[INLINE_CODE_2]": "`multipart/form-data`",
  "[INLINE_CODE_3]": "`Content-Type`",
  "[INLINE_CODE_4]": "`application/json`",
  "[INLINE_CODE_5]": "`text/xml`",
  "[INLINE_CODE_6]": "`application/x-www-form-urlencoded`",
  "[INLINE_CODE_7]": "`Authorization`",
  "[INLINE_CODE_8]": "`https://www.galacticresorts.com/api/Reservation`",
  "[INLINE_CODE_9]": "`Host`",
  "[INLINE_CODE_10]": "`Accept-Encoding`",
  "[INLINE_CODE_11]": "`Host`",
  "[INLINE_CODE_12]": "`Content-Type`",
  "[INLINE_CODE_13]": "`Authorization`",
  "[INLINE_CODE_14]": "`Accept-Encoding`",
  "[INLINE_CODE_15]": "`x-www-form-urlencoded`",
  "[INLINE_CODE_16]": "`[SYSTEM_VAR_1]`",
  "[INLINE_CODE_17]": "`[SYSTEM_VAR_2]`",
  "[INLINE_CODE_18]": "`itemGuid`",
  "[INLINE_CODE_19]": "`{\"result\":\"processing\"}`",
  "[INLINE_CODE_20]": "`{\"result\":\"success\"}`",
  "[INLINE_CODE_21]": "`multipart/form-data`",
  "[INLINE_CODE_22]": "`Content-Length`",
  "[INLINE_CODE_23]": "`Content-Type: multipart/form-data`",
  "[INLINE_CODE_24]": "`Content-Disposition`",
  "[ANCHOR_1]": "{id=\"request-headers\"}",
  "[ANCHOR_2]": "{id=\"import-curl\"}",
  "[ANCHOR_3]": "{id=\"msaretry\"}",
  "[URL_1]": "https://\"",
  "[URL_2]": "http://\""
}